louvre_vision/__init__.py
louvre_vision/config.py
louvre_vision/data_models.py
louvre_vision/dataset.py
louvre_vision/errors.py
louvre_vision/file_methods.py
louvre_vision/images.py
louvre_vision/logs.py
louvre_vision/metadata.py
louvre_vision/methods.py
louvre_vision/predict.py
louvre_vision/train.py
elvia_louvre_vision-0.9.4.dist-info/METADATA
elvia_louvre_vision-0.9.4.dist-info/WHEEL
elvia_louvre_vision-0.9.4.dist-info/top_level.txt
elvia_louvre_vision-0.9.4.dist-info/RECORD
