Metadata-Version: 2.1
Name: elvia-louvre-vision
Version: 0.9.4
Summary: elvia-louvre-vision Python package
Author: Elvia
Requires-Dist: azure-cognitiveservices-vision-customvision (==3.1.0)
Requires-Dist: elvia-louvre (>=0.3.1)
Requires-Dist: imageio (>=2.8.0)
Requires-Dist: imgaug (>=0.4.0)
Requires-Dist: numpy (>=1.20.2)
Requires-Dist: pillow (>=9.3.0)
